ChatConnector/__init__.py
ChatConnector/chatClient.py
ChatConnector-0.0.1.dist-info/METADATA
ChatConnector-0.0.1.dist-info/WHEEL
ChatConnector-0.0.1.dist-info/top_level.txt
ChatConnector-0.0.1.dist-info/RECORD
