Metadata-Version: 2.1
Name: ChatConnector
Version: 0.0.1
Summary: A chat client that connects to Chat Connector Network.
Author: TheShulkerBox
Author-email: <shivek.sethi.saraf@gmail.com>
Keywords: python,chat client,chat connector,chat,sockets
Classifier: Development Status :: 5 - Production/Stable
Classifier: Intended Audience :: Telecommunications Industry
Classifier: Programming Language :: Python :: 3
Classifier: Operating System :: Unix
Classifier: Operating System :: MacOS :: MacOS X
Classifier: Operating System :: Microsoft :: Windows
Requires-Dist: pygame
Requires-Dist: easygui
